git_prune/__init__.py
git_prune/main.py
git_prune-1.0.1.dist-info/licenses/LICENSE
git_prune-1.0.1.dist-info/METADATA
git_prune-1.0.1.dist-info/WHEEL
git_prune-1.0.1.dist-info/entry_points.txt
git_prune-1.0.1.dist-info/top_level.txt
git_prune-1.0.1.dist-info/RECORD
