Metadata-Version: 2.4
Name: git-prune
Version: 1.0.1
Summary: Clean up your local git branches to match the remote with one command.
Author: Richard
License-Expression: MIT
License-File: LICENSE
Requires-Dist: click>=8.1.8
Dynamic: license-file
